{
	"name": "2X-7KPR (Tooex)",
	"id": "137213",
	"side": "DS",
	"type": "Character",
	"subtype": "Droid",
	"card_set": "Special Edition",
	"icons": "",
	"Lore": "'Basic security droid. Monitors perimeter sensors and floodlights at Imperial outposts. Responsible for maintenance of security devices. Stolen from Jabba.',",
	"Rarity": "C",
	"Text": "'Where present under ''nighttime conditions,'' each of your Imperials and aliens at same planet site is power +2 and immune to attrition < 3.',",
	"Destiny": "3",
	"Power": "0",
	"Ability": "",
	"Deploy": "2",
	"Forfeit": "2",
	"Hyperspeed": "",
	"Maneuver": "",
	"Parsec": "",
	"path": "/starwars/SpecialEdition-Dark/t_2x7kprtooex",
	"uniqueness": "",
	"ModelType": "Security",
	"ObjectiveText1": "",
	"ObjectiveText2": "",
	"ForceIconsD": "",
	"ForceIconsL": "",
	"Armor": "",
	"CreatureDV": "",
	"Landspeed": "",
	"Politics": "",
	"Influence": "",
	"LocationDStext": "",
	"LocationLStext": "",
	"ObjectiveFrontName": "",
	"ObjectiveBackName": "",
	"Luck": "",
	"Shadow": "",
}
