{
	"name": "Arcona",
	"id": "135118",
	"side": "LS",
	"type": "Character",
	"subtype": "Alien",
	"card_set": "A New Hope",
	"icons": "",
	"Lore": "'Unut Poll is a typical male Arcona. Unlike many other Arcona, he has avoided salt. Scout known to cooperate with Alliance operatives.',",
	"Rarity": "C2",
	"Text": "'Power +1 under ''nighttime conditions.'' May move away from a battle at same site as a ''react.''',",
	"Destiny": "3",
	"Power": "1",
	"Ability": "1",
	"Deploy": "2",
	"Forfeit": "2",
	"Hyperspeed": "",
	"Maneuver": "",
	"Parsec": "",
	"path": "/starwars/ANewHope-Light/t_arcona",
	"uniqueness": "•••",
	"ModelType": "",
	"ObjectiveText1": "",
	"ObjectiveText2": "",
	"ForceIconsD": "",
	"ForceIconsL": "",
	"Armor": "",
	"CreatureDV": "",
	"Landspeed": "",
	"Politics": "",
	"Influence": "",
	"LocationDStext": "",
	"LocationLStext": "",
	"ObjectiveFrontName": "",
	"ObjectiveBackName": "",
	"Luck": "",
	"Shadow": "",
}
