{
	"name": "Asteroid Field",
	"id": "136517",
	"side": "LS",
	"type": "Location",
	"subtype": "Sector",
	"card_set": "Dagobah",
	"icons": "[Space]",
	"Lore": "'',",
	"Rarity": "C",
	"Text": "'',",
	"Destiny": "0",
	"Power": "",
	"Ability": "",
	"Deploy": "",
	"Forfeit": "",
	"Hyperspeed": "",
	"Maneuver": "",
	"Parsec": "",
	"path": "/starwars/Dagobah-Light/t_asteroidfield",
	"uniqueness": "<><><>",
	"ModelType": "",
	"ObjectiveText1": "",
	"ObjectiveText2": "",
	"ForceIconsD": "1",
	"ForceIconsL": "1",
	"Armor": "",
	"CreatureDV": "",
	"Landspeed": "",
	"Politics": "",
	"Influence": "",
	"LocationDStext": "'Asteroid Rules' in effect here.",
	"LocationLStext": "'Asteroid Rules' in effect here. If you control, may cancel Force drain at related system.",
	"ObjectiveFrontName": "",
	"ObjectiveBackName": "",
	"Luck": "",
	"Shadow": "",
}
