{
	"name": "Beru Stew",
	"id": "136121",
	"side": "LS",
	"type": "Interrupt",
	"subtype": "Lost",
	"card_set": "Premiere",
	"icons": "",
	"Lore": "'Moisture farmers grow enough food to sustain Tatooine''s population. Beru Lars has devised many dishes using herbs and roots naturally found in Tatooine''s desert.',",
	"Rarity": "U2",
	"Text": "'Each player must immediately activate 2 Force. Also, you may activate 1 additional Force for each Beru Lars, Owen Lars or Hydroponics Station on table.',",
	"Destiny": "4",
	"Power": "",
	"Ability": "",
	"Deploy": "",
	"Forfeit": "",
	"Hyperspeed": "",
	"Maneuver": "",
	"Parsec": "",
	"path": "/starwars/Premiere-Light/t_berustew",
	"uniqueness": "•",
	"ModelType": "",
	"ObjectiveText1": "",
	"ObjectiveText2": "",
	"ForceIconsD": "",
	"ForceIconsL": "",
	"Armor": "",
	"CreatureDV": "",
	"Landspeed": "",
	"Politics": "",
	"Influence": "",
	"LocationDStext": "",
	"LocationLStext": "",
	"ObjectiveFrontName": "",
	"ObjectiveBackName": "",
	"Luck": "",
	"Shadow": "",
}
