{
	"name": "BlasTech E-11B Blaster Rifle",
	"id": "136905",
	"side": "LS",
	"type": "Weapon",
	"subtype": "Character",
	"card_set": "Endor",
	"icons": "",
	"Lore": "'Modified by Alliance armorers who defected from the BlasTech corporation. Expensive cooling system incorporated to allow higher fire rate.',",
	"Rarity": "C",
	"Text": "'Use 2 Force to deploy on your scout warrior. May target a character, creature or vehicle using 1 Force. Draw destiny. Target hit if destiny > defense value. May fire repeatedly for 2 Force each time.',",
	"Destiny": "2",
	"Power": "",
	"Ability": "",
	"Deploy": "",
	"Forfeit": "",
	"Hyperspeed": "",
	"Maneuver": "",
	"Parsec": "",
	"path": "/starwars/Endor-Light/t_blasteche11bblasterrifle",
	"uniqueness": "",
	"ModelType": "",
	"ObjectiveText1": "",
	"ObjectiveText2": "",
	"ForceIconsD": "",
	"ForceIconsL": "",
	"Armor": "",
	"CreatureDV": "",
	"Landspeed": "",
	"Politics": "",
	"Influence": "",
	"LocationDStext": "",
	"LocationLStext": "",
	"ObjectiveFrontName": "",
	"ObjectiveBackName": "",
	"Luck": "",
	"Shadow": "",
}
