{
	"name": "Bossk",
	"id": "137011",
	"side": "DS",
	"type": "Character",
	"subtype": "Alien",
	"card_set": "Dagobah",
	"icons": "Pilot  [Warrior]",
	"Lore": "'Male Trandoshan bounty hunter. Strong but clumsy. Extremely proud and arrogant. Suffered a humiliating defeat at the hands of Chewbacca and his partner Han Solo.',",
	"Rarity": "R",
	"Text": "'Adds 2 to power of anything he pilots. When piloting Hound''s Tooth, draws one battle destiny if not able to otherwise. Adds 1 to attrition against opponent in battles at same site. While present, may reduce Chewie''s forfeit to zero while here.',",
	"Destiny": "1",
	"Power": "4",
	"Ability": "2",
	"Deploy": "4",
	"Forfeit": "3",
	"Hyperspeed": "",
	"Maneuver": "",
	"Parsec": "",
	"path": "/starwars/Dagobah-Dark/t_bossk",
	"uniqueness": "•",
	"ModelType": "",
	"ObjectiveText1": "",
	"ObjectiveText2": "",
	"ForceIconsD": "",
	"ForceIconsL": "",
	"Armor": "",
	"CreatureDV": "",
	"Landspeed": "",
	"Politics": "",
	"Influence": "",
	"LocationDStext": "",
	"LocationLStext": "",
	"ObjectiveFrontName": "",
	"ObjectiveBackName": "",
	"Luck": "",
	"Shadow": "",
}
