{
	"name": "Desperate Times",
	"id": "136138",
	"side": "LS",
	"type": "Interrupt",
	"subtype": "Lost",
	"card_set": "Reflections III",
	"icons": "",
	"Lore": "'Han''s best tactic when outnumbered? Shoot first and don''t worry about asking questions later.',",
	"Rarity": "PM",
	"Text": "'During a battle where your opponent has more characters participating than you, fire (for free) one blaster that cannot fire repeatedly, even if that blaster was already fired this battle. Add 1 to your total weapon destiny.',",
	"Destiny": "4",
	"Power": "",
	"Ability": "",
	"Deploy": "",
	"Forfeit": "",
	"Hyperspeed": "",
	"Maneuver": "",
	"Parsec": "",
	"path": "/starwars/ReflectionsIII-Light/t_desperatetimes",
	"uniqueness": "•",
	"ModelType": "",
	"ObjectiveText1": "",
	"ObjectiveText2": "",
	"ForceIconsD": "",
	"ForceIconsL": "",
	"Armor": "",
	"CreatureDV": "",
	"Landspeed": "",
	"Politics": "",
	"Influence": "",
	"LocationDStext": "",
	"LocationLStext": "",
	"ObjectiveFrontName": "",
	"ObjectiveBackName": "",
	"Luck": "",
	"Shadow": "",
}
