{
	"name": "General Jar Jar",
	"id": "135174",
	"side": "LS",
	"type": "Character",
	"subtype": "Alien",
	"card_set": "Theed Palace",
	"icons": "[Warrior]  [Episode 1]",
	"Lore": "'After uniting the Gungans and the Noboo, Boss Nass promoted Jar Jar Binks to General. He''s still a bit clumsy.',",
	"Rarity": "R",
	"Text": "'Once per game may take Brisky Morning Munchen into hand from Reserve Deck; reshuffle. Once per battle, may use 1 Force to target an opponent''s droid present. Both players draw destiny. If your destiny + 1 > opponent''s destiny, target lost.',",
	"Destiny": "2",
	"Power": "4",
	"Ability": "3",
	"Deploy": "2",
	"Forfeit": "4",
	"Hyperspeed": "",
	"Maneuver": "",
	"Parsec": "",
	"path": "/starwars/TheedPalace-Light/t_generaljarjar",
	"uniqueness": "•",
	"ModelType": "",
	"ObjectiveText1": "",
	"ObjectiveText2": "",
	"ForceIconsD": "",
	"ForceIconsL": "",
	"Armor": "",
	"CreatureDV": "",
	"Landspeed": "",
	"Politics": "",
	"Influence": "",
	"LocationDStext": "",
	"LocationLStext": "",
	"ObjectiveFrontName": "",
	"ObjectiveBackName": "",
	"Luck": "",
	"Shadow": "",
}
