{
	"name": "Jabba, This Is Your Last Chance!",
	"id": "136082",
	"side": "LS",
	"type": "Effect",
	"subtype": "Starting",
	"card_set": "Virtual Block 6",
	"icons": "[Jabba's Palace]",
	"Lore": "'With a quick motion of his hand, Luke signaled Artoo and dramatically changed the situation.',",
	"Rarity": "C",
	"Text": "'Deploy on table with 5 cards from outside your deck face down under here. Twice per game, may play a Defensive Shield from here (as if from hand). If Quiet Mining Colony or Independent Operation on table, lightsabers may not add to Force drains or ''swing'' more than once per battle. Cloud City Celebration is canceled.',",
	"Destiny": "5",
	"Power": "",
	"Ability": "",
	"Deploy": "",
	"Forfeit": "",
	"Hyperspeed": "",
	"Maneuver": "",
	"Parsec": "",
	"path": "/starwars/Virtual6-Light/t_jabbathisisyourlastchance",
	"uniqueness": "•",
	"ModelType": "",
	"ObjectiveText1": "",
	"ObjectiveText2": "",
	"ForceIconsD": "",
	"ForceIconsL": "",
	"Armor": "",
	"CreatureDV": "",
	"Landspeed": "",
	"Politics": "",
	"Influence": "",
	"LocationDStext": "",
	"LocationLStext": "",
	"ObjectiveFrontName": "",
	"ObjectiveBackName": "",
	"Luck": "",
	"Shadow": "",
}
