{
	"name": "Kashyyyk",
	"id": "138526",
	"side": "DS",
	"type": "Location",
	"subtype": "System",
	"card_set": "A New Hope",
	"icons": "[Planet]",
	"Lore": "'',",
	"Rarity": "C1",
	"Text": "'',",
	"Destiny": "0",
	"Power": "",
	"Ability": "",
	"Deploy": "",
	"Forfeit": "",
	"Hyperspeed": "",
	"Maneuver": "",
	"Parsec": "6",
	"path": "/starwars/ANewHope-Dark/t_kashyyyk",
	"uniqueness": "•",
	"ModelType": "",
	"ObjectiveText1": "",
	"ObjectiveText2": "",
	"ForceIconsD": "2",
	"ForceIconsL": "1",
	"Armor": "",
	"CreatureDV": "",
	"Landspeed": "",
	"Politics": "",
	"Influence": "",
	"LocationDStext": "Force drain +1 here. If you control, all Wookiees on table are forfeit -3.",
	"LocationLStext": "Your starships with any Wookiee aboard are power and forfeit +2 here.",
	"ObjectiveFrontName": "",
	"ObjectiveBackName": "",
	"Luck": "",
	"Shadow": "",
}
