{
	"name": "Kashyyyk Operative",
	"id": "137086",
	"side": "DS",
	"type": "Character",
	"subtype": "Alien",
	"card_set": "Special Edition",
	"icons": "[Warrior]",
	"Lore": "'Hunters who track down escaped Wookiee slaves and report on their location. The Empire and Trandoshans pay a high price for that kind of information.',",
	"Rarity": "U",
	"Text": "'While at a Kashyyyk site: adds 1 to your Force drains there, is power +1 (or +2 if your Trandoshan is on Kashyyyk) and, once during each of your deploy phases, may deploy one site to Kashyyyk from Reserve Deck- reshuffle.',",
	"Destiny": "3",
	"Power": "1",
	"Ability": "1",
	"Deploy": "1",
	"Forfeit": "2",
	"Hyperspeed": "",
	"Maneuver": "",
	"Parsec": "",
	"path": "/starwars/SpecialEdition-Dark/t_kashyyykoperative",
	"uniqueness": "",
	"ModelType": "",
	"ObjectiveText1": "",
	"ObjectiveText2": "",
	"ForceIconsD": "",
	"ForceIconsL": "",
	"Armor": "",
	"CreatureDV": "",
	"Landspeed": "",
	"Politics": "",
	"Influence": "",
	"LocationDStext": "",
	"LocationLStext": "",
	"ObjectiveFrontName": "",
	"ObjectiveBackName": "",
	"Luck": "",
	"Shadow": "",
}
