{
	"name": "Naboo Celebration",
	"id": "135920",
	"side": "LS",
	"type": "Effect",
	"subtype": "",
	"card_set": "Theed Palace",
	"icons": "[Episode 1]",
	"Lore": "'The heroic actions of Amidala''s forces and Boss Nass'' army saved Naboo from the Trade Federation. Definitely a cause for celebration!',",
	"Rarity": "R",
	"Text": "'Deploy on table. If Amidala at a Theed Palace site (or Boss Nass at an exterior Naboo site), opponent''s cards with ability deploy +2 there. Once during battle at a Naboo site, if you just drew a Gungan or Royal Naboo Security for battle destiny, opponent loses 1 Force.',",
	"Destiny": "5",
	"Power": "",
	"Ability": "",
	"Deploy": "",
	"Forfeit": "",
	"Hyperspeed": "",
	"Maneuver": "",
	"Parsec": "",
	"path": "/starwars/TheedPalace-Light/t_naboocelebration",
	"uniqueness": "•",
	"ModelType": "",
	"ObjectiveText1": "",
	"ObjectiveText2": "",
	"ForceIconsD": "",
	"ForceIconsL": "",
	"Armor": "",
	"CreatureDV": "",
	"Landspeed": "",
	"Politics": "",
	"Influence": "",
	"LocationDStext": "",
	"LocationLStext": "",
	"ObjectiveFrontName": "",
	"ObjectiveBackName": "",
	"Luck": "",
	"Shadow": "",
}
