{
	"name": "Naboo Security Officer Blaster",
	"id": "136943",
	"side": "LS",
	"type": "Weapon",
	"subtype": "Character",
	"card_set": "Coruscant",
	"icons": "[Episode 1]",
	"Lore": "'Used primarily by high-ranking Naboo security officers, and known for its precision targeting.',",
	"Rarity": "C",
	"Text": "'Use 1 Force to deploy on your warrior. May target a character, creature, vehicle for free. Draw destiny. Add 1 if fired by a leader. Target hit if total destiny > defense value.',",
	"Destiny": "5",
	"Power": "",
	"Ability": "",
	"Deploy": "",
	"Forfeit": "",
	"Hyperspeed": "",
	"Maneuver": "",
	"Parsec": "",
	"path": "/starwars/Coruscant-Light/t_naboosecurityofficerblaster",
	"uniqueness": "",
	"ModelType": "",
	"ObjectiveText1": "",
	"ObjectiveText2": "",
	"ForceIconsD": "",
	"ForceIconsL": "",
	"Armor": "",
	"CreatureDV": "",
	"Landspeed": "",
	"Politics": "",
	"Influence": "",
	"LocationDStext": "",
	"LocationLStext": "",
	"ObjectiveFrontName": "",
	"ObjectiveBackName": "",
	"Luck": "",
	"Shadow": "",
}
