{
	"name": "Off The Edge",
	"id": "136188",
	"side": "LS",
	"type": "Interrupt",
	"subtype": "Lost",
	"card_set": "Cloud City",
	"icons": "",
	"Lore": "'Despite the brutal attacks of the Dark Lord, dying on Cloud City was not Luke''s destiny.',",
	"Rarity": "R",
	"Text": "'Target one of your characters at a Cloud City site. Draw destiny. If destiny > character''s destiny number, retrieve Force equal to the distance. If destiny < character''s destiny number, lose difference. If destiny = character''s destiny number, character is lost.',",
	"Destiny": "2",
	"Power": "",
	"Ability": "",
	"Deploy": "",
	"Forfeit": "",
	"Hyperspeed": "",
	"Maneuver": "",
	"Parsec": "",
	"path": "/starwars/CloudCity-Light/t_offtheedge",
	"uniqueness": "•",
	"ModelType": "",
	"ObjectiveText1": "",
	"ObjectiveText2": "",
	"ForceIconsD": "",
	"ForceIconsL": "",
	"Armor": "",
	"CreatureDV": "",
	"Landspeed": "",
	"Politics": "",
	"Influence": "",
	"LocationDStext": "",
	"LocationLStext": "",
	"ObjectiveFrontName": "",
	"ObjectiveBackName": "",
	"Luck": "",
	"Shadow": "",
}
