{
	"name": "Plo Koon",
	"id": "135377",
	"side": "LS",
	"type": "Character",
	"subtype": "Jedi Master",
	"card_set": "Coruscant",
	"icons": "[Warrior]  [Episode 1]",
	"Lore": "'Kel Dor Jedi Council member descended from a long line of Jedi. Known for exceptional sensory skills, Plo Koon''s control of the Force is unmatched by most.',",
	"Rarity": "R",
	"Text": "'Deploys only to Jedi Council Chamber. While at Jedi Council Chamber, immune to attrition and, once per turn if a weapon or battle destiny was just drawn, may cancel and cause a re-draw.',",
	"Destiny": "2",
	"Power": "5",
	"Ability": "7",
	"Deploy": "6",
	"Forfeit": "5",
	"Hyperspeed": "",
	"Maneuver": "",
	"Parsec": "",
	"path": "/starwars/Coruscant-Light/t_plokoon",
	"uniqueness": "•",
	"ModelType": "",
	"ObjectiveText1": "",
	"ObjectiveText2": "",
	"ForceIconsD": "",
	"ForceIconsL": "",
	"Armor": "",
	"CreatureDV": "",
	"Landspeed": "",
	"Politics": "",
	"Influence": "",
	"LocationDStext": "",
	"LocationLStext": "",
	"ObjectiveFrontName": "",
	"ObjectiveBackName": "",
	"Luck": "",
	"Shadow": "",
}
