{
	"name": "Polarized Negative Power Coupling",
	"id": "135938",
	"side": "LS",
	"type": "Effect",
	"subtype": "",
	"card_set": "Dagobah",
	"icons": "",
	"Lore": "'Imbalance in a converter''s inverse energy field can improperly polarize the negative axis, causing hyperdrive failure. Replacement often requires an inverted engineer.',",
	"Rarity": "R",
	"Text": "'Deploy on table. Turn every Used Pile face up. All subsequent cards placed in Used Piles are also turned face up. (Players must commit to using cards before revealing them.) Turn used cards face down whenever they are re-circulated.',",
	"Destiny": "4",
	"Power": "",
	"Ability": "",
	"Deploy": "",
	"Forfeit": "",
	"Hyperspeed": "",
	"Maneuver": "",
	"Parsec": "",
	"path": "/starwars/Dagobah-Light/t_polarizednegativepowercoupling",
	"uniqueness": "",
	"ModelType": "",
	"ObjectiveText1": "",
	"ObjectiveText2": "",
	"ForceIconsD": "",
	"ForceIconsL": "",
	"Armor": "",
	"CreatureDV": "",
	"Landspeed": "",
	"Politics": "",
	"Influence": "",
	"LocationDStext": "",
	"LocationLStext": "",
	"ObjectiveFrontName": "",
	"ObjectiveBackName": "",
	"Luck": "",
	"Shadow": "",
}
