{
	"name": "Power Of The Hutt",
	"id": "137811",
	"side": "DS",
	"type": "Effect",
	"subtype": "",
	"card_set": "Jabba's Palace Sealed Deck",
	"icons": "",
	"Lore": "'Jabba runs his organization out of a palace built around a B''omarr monastery. His fortress near the border of the western Dune Sea is safe from enemies in Mos Eisley.',",
	"Rarity": "PM",
	"Text": "'Deploy on table. Once during each of your turns, may deploy one Boelo, Bib, Ephant Mon, Jabba''s Sail Barge, Jabba''s Space Cruiser, or Hutt Influence from Reserve Deck; reshuffle. Also, your aliens aboard Jabba''s Sail Barge are immune to attrition < 6. (Immune to Alter.)',",
	"Destiny": "4",
	"Power": "",
	"Ability": "",
	"Deploy": "",
	"Forfeit": "",
	"Hyperspeed": "",
	"Maneuver": "",
	"Parsec": "",
	"path": "/starwars/JabbasPalaceSealedDeck-Dark/t_powerofthehutt",
	"uniqueness": "•",
	"ModelType": "",
	"ObjectiveText1": "",
	"ObjectiveText2": "",
	"ForceIconsD": "",
	"ForceIconsL": "",
	"Armor": "",
	"CreatureDV": "",
	"Landspeed": "",
	"Politics": "",
	"Influence": "",
	"LocationDStext": "",
	"LocationLStext": "",
	"ObjectiveFrontName": "",
	"ObjectiveBackName": "",
	"Luck": "",
	"Shadow": "",
}
