{
	"name": "Quick Draw (V)",
	"id": "135942",
	"side": "LS",
	"type": "Effect",
	"subtype": "",
	"card_set": "Virtual Block 4",
	"icons": "[Dagobah]",
	"Lore": "'It''s high noon on Dagobah, his droid''s reined in and Luke''s got a fistful of credits.',",
	"Rarity": "C",
	"Text": "'Unless Inner Strength on table, deploy on table.  Your lightsabers may target vehicles using 1 Force (each destiny draw is -2).  Once per turn, may lose 1 Force to deploy a character weapon (except a grenade) from Lost Pile.  Once per turn, may deploy [Virtual Block 1] Sai''torr Kal Fas from Reserve Deck; reshuffle. (Immune to Alter.)(Original concept by Lee Edwards - Florida State Winner 2004)(Errata Text - September 9th, 2009)',",
	"Destiny": "3",
	"Power": "",
	"Ability": "",
	"Deploy": "",
	"Forfeit": "",
	"Hyperspeed": "",
	"Maneuver": "",
	"Parsec": "",
	"path": "/starwars/Virtual4-Light/t_quickdraw",
	"uniqueness": "",
	"ModelType": "",
	"ObjectiveText1": "",
	"ObjectiveText2": "",
	"ForceIconsD": "",
	"ForceIconsL": "",
	"Armor": "",
	"CreatureDV": "",
	"Landspeed": "",
	"Politics": "",
	"Influence": "",
	"LocationDStext": "",
	"LocationLStext": "",
	"ObjectiveFrontName": "",
	"ObjectiveBackName": "",
	"Luck": "",
	"Shadow": "",
}
