{
	"name": "Rappertunie",
	"id": "137136",
	"side": "DS",
	"type": "Character",
	"subtype": "Alien",
	"card_set": "Special Edition",
	"icons": "",
	"Lore": "'Shawda Ubb musician from Manpha. Plays growdi. Real name Rapotwanalantonee. When cornered in a fight, he can spit a paralyzing poison.',",
	"Rarity": "U",
	"Text": "'Where present, adds X to Force opponent must use to initiate battle, where X = number of musicians present. May target one non-droid character resent in battle. Draw destiny. If destiny > defense balue, target is power = 0 this battle.',",
	"Destiny": "3",
	"Power": "3",
	"Ability": "1",
	"Deploy": "2",
	"Forfeit": "2",
	"Hyperspeed": "",
	"Maneuver": "",
	"Parsec": "",
	"path": "/starwars/SpecialEdition-Dark/t_rappertunie",
	"uniqueness": "•",
	"ModelType": "",
	"ObjectiveText1": "",
	"ObjectiveText2": "",
	"ForceIconsD": "",
	"ForceIconsL": "",
	"Armor": "",
	"CreatureDV": "",
	"Landspeed": "",
	"Politics": "",
	"Influence": "",
	"LocationDStext": "",
	"LocationLStext": "",
	"ObjectiveFrontName": "",
	"ObjectiveBackName": "",
	"Luck": "",
	"Shadow": "",
}
