{
	"name": "Rolling, Rolling, Rolling",
	"id": "138203",
	"side": "DS",
	"type": "Interrupt",
	"subtype": "Used",
	"card_set": "Theed Palace",
	"icons": "[Episode 1]",
	"Lore": "'The Colicoids from Colla IV modeled destroyer droids after themselves in that they can roll up into a ball and move swiftly into a conflict.',",
	"Rarity": "R",
	"Text": "'Take any non-unique destroyer droid into hand from Reserve Deck; reshuffle. OR During your deploy phase, relocate your destroyer droid to an adjacent site.',",
	"Destiny": "5",
	"Power": "",
	"Ability": "",
	"Deploy": "",
	"Forfeit": "",
	"Hyperspeed": "",
	"Maneuver": "",
	"Parsec": "",
	"path": "/starwars/TheedPalace-Dark/t_rollingrollingrolling",
	"uniqueness": "•",
	"ModelType": "",
	"ObjectiveText1": "",
	"ObjectiveText2": "",
	"ForceIconsD": "",
	"ForceIconsL": "",
	"Armor": "",
	"CreatureDV": "",
	"Landspeed": "",
	"Politics": "",
	"Influence": "",
	"LocationDStext": "",
	"LocationLStext": "",
	"ObjectiveFrontName": "",
	"ObjectiveBackName": "",
	"Luck": "",
	"Shadow": "",
}
