{
	"name": "Senate Hovercam",
	"id": "135974",
	"side": "LS",
	"type": "Effect",
	"subtype": "",
	"card_set": "Theed Palace",
	"icons": "[Episode 1]",
	"Lore": "'Senate hovercams report back to Chancellor Valorum at the conclusion of a Senate session. Mysteriously, the droid monitoring Amidala in the Senate never reported back.',",
	"Rarity": "R",
	"Text": "'Deploy on Galactic Senate. Amidala is politics +1 here. While you have a senate majority, your Force generation here is +3. Place Effect in Lost Pile if opponent controls this location.',",
	"Destiny": "3",
	"Power": "",
	"Ability": "",
	"Deploy": "",
	"Forfeit": "",
	"Hyperspeed": "",
	"Maneuver": "",
	"Parsec": "",
	"path": "/starwars/TheedPalace-Light/t_senatehovercam",
	"uniqueness": "•",
	"ModelType": "",
	"ObjectiveText1": "",
	"ObjectiveText2": "",
	"ForceIconsD": "",
	"ForceIconsL": "",
	"Armor": "",
	"CreatureDV": "",
	"Landspeed": "",
	"Politics": "",
	"Influence": "",
	"LocationDStext": "",
	"LocationLStext": "",
	"ObjectiveFrontName": "",
	"ObjectiveBackName": "",
	"Luck": "",
	"Shadow": "",
}
