{
	"name": "Skrilling",
	"id": "137154",
	"side": "DS",
	"type": "Character",
	"subtype": "Alien",
	"card_set": "Jabba's Palace",
	"icons": "[Warrior]",
	"Lore": "'Regarded as whiners. Skrillings are a scavenger species. Steal from corpses left behind on battlefields. Feed on carrion and uncooked meat. Avoided by many species.',",
	"Rarity": "C",
	"Text": "'Once per turn, may steal a weapon or device from an opponent''s character just lost or forfeited where present. When you play Tusken Scavengers, may steal vehicles, weapons and devices found (place them in your Used Pile).',",
	"Destiny": "4",
	"Power": "2",
	"Ability": "1",
	"Deploy": "2",
	"Forfeit": "2",
	"Hyperspeed": "",
	"Maneuver": "",
	"Parsec": "",
	"path": "/starwars/JabbasPalace-Dark/t_skrilling",
	"uniqueness": "",
	"ModelType": "",
	"ObjectiveText1": "",
	"ObjectiveText2": "",
	"ForceIconsD": "",
	"ForceIconsL": "",
	"Armor": "",
	"CreatureDV": "",
	"Landspeed": "",
	"Politics": "",
	"Influence": "",
	"LocationDStext": "",
	"LocationLStext": "",
	"ObjectiveFrontName": "",
	"ObjectiveBackName": "",
	"Luck": "",
	"Shadow": "",
}
