{
	"name": "Strike Blocked",
	"id": "136375",
	"side": "LS",
	"type": "Interrupt",
	"subtype": "Used",
	"card_set": "Reflections III",
	"icons": "[Episode 1]",
	"Lore": "'At times it was calculated defense, at others it was simply survival.',",
	"Rarity": "PM",
	"Text": "'Take top card of Force Pile into hand. OR If opponent just revealed a combat card, it is canceled (place in opponent''s Used Pile) and opponent must draw destiny instead (that destiny is reduced by 1). OR Cancel Maul Strikes, Dark Strike, or You Are Beaten.',",
	"Destiny": "3",
	"Power": "",
	"Ability": "",
	"Deploy": "",
	"Forfeit": "",
	"Hyperspeed": "",
	"Maneuver": "",
	"Parsec": "",
	"path": "/starwars/ReflectionsIII-Light/t_strikeblocked",
	"uniqueness": "•",
	"ModelType": "",
	"ObjectiveText1": "",
	"ObjectiveText2": "",
	"ForceIconsD": "",
	"ForceIconsL": "",
	"Armor": "",
	"CreatureDV": "",
	"Landspeed": "",
	"Politics": "",
	"Influence": "",
	"LocationDStext": "",
	"LocationLStext": "",
	"ObjectiveFrontName": "",
	"ObjectiveBackName": "",
	"Luck": "",
	"Shadow": "",
}
