{
	"name": "Sullust",
	"id": "138539",
	"side": "DS",
	"type": "Location",
	"subtype": "System",
	"card_set": "Death Star II",
	"icons": "[Planet]",
	"Lore": "'',",
	"Rarity": "C",
	"Text": "'',",
	"Destiny": "0",
	"Power": "",
	"Ability": "",
	"Deploy": "",
	"Forfeit": "",
	"Hyperspeed": "",
	"Maneuver": "",
	"Parsec": "7",
	"path": "/starwars/DeathStarII-Dark/t_sullust",
	"uniqueness": "•",
	"ModelType": "",
	"ObjectiveText1": "",
	"ObjectiveText2": "",
	"ForceIconsD": "2",
	"ForceIconsL": "2",
	"Armor": "",
	"CreatureDV": "",
	"Landspeed": "",
	"Politics": "",
	"Influence": "",
	"LocationDStext": "If you control when Haven is canceled, opponent loses 8 Force.",
	"LocationLStext": "Immune to Revolution.",
	"ObjectiveFrontName": "",
	"ObjectiveBackName": "",
	"Luck": "",
	"Shadow": "",
}
