{
	"name": "Tatooine: Mos Eisley (V)",
	"id": "138498",
	"side": "DS",
	"type": "Location",
	"subtype": "Site",
	"card_set": "Virtual Block 1",
	"icons": "[Interior]  [Exterior]  [Planet]  [Scomp Link]",
	"Lore": "'',",
	"Rarity": "C1",
	"Text": "'',",
	"Destiny": "0",
	"Power": "",
	"Ability": "",
	"Deploy": "",
	"Forfeit": "",
	"Hyperspeed": "",
	"Maneuver": "",
	"Parsec": "",
	"path": "/starwars/Virtual1-Dark/t_tatooinemoseisley",
	"uniqueness": "•",
	"ModelType": "",
	"ObjectiveText1": "",
	"ObjectiveText2": "",
	"ForceIconsD": "1",
	"ForceIconsL": "1",
	"Armor": "",
	"CreatureDV": "",
	"Landspeed": "",
	"Politics": "",
	"Influence": "",
	"LocationDStext": "Once per turn, when a player's Landing Craft takes off or lands here, that player may retrieve 1 Force",
	"LocationLStext": "Immune to Revolution. If a stormtrooper here, you must first use 2 Force to deploy a weapon or device at same or adjacent site.",
	"ObjectiveFrontName": "",
	"ObjectiveBackName": "",
	"Luck": "",
	"Shadow": "",
}
