{
	"name": "Tatooine: Cantina (V)",
	"id": "136630",
	"side": "LS",
	"type": "Location",
	"subtype": "Site",
	"card_set": "Virtual Block 8",
	"icons": "[Interior]  [Planet]",
	"Lore": "'',",
	"Rarity": "R2",
	"Text": "'',",
	"Destiny": "0",
	"Power": "",
	"Ability": "",
	"Deploy": "",
	"Forfeit": "",
	"Hyperspeed": "",
	"Maneuver": "",
	"Parsec": "",
	"path": "/starwars/Virtual8-Light/t_tatooinecantina",
	"uniqueness": "•",
	"ModelType": "",
	"ObjectiveText1": "",
	"ObjectiveText2": "",
	"ForceIconsD": "2",
	"ForceIconsL": "2",
	"Armor": "",
	"CreatureDV": "",
	"Landspeed": "",
	"Politics": "",
	"Influence": "",
	"LocationDStext": "You lose no Force to Force Drains at opponent's Kessel system. May not be converted.",
	"LocationLStext": "[Virtual Block 8] Scoundrels are smugglers. May use 1 Force to deploy Mose Eisley from reserve deck; reshuffle. Immune to Revolution.",
	"ObjectiveFrontName": "",
	"ObjectiveBackName": "",
	"Luck": "",
	"Shadow": "",
}
