{
	"name": "The Professor",
	"id": "136003",
	"side": "LS",
	"type": "Effect",
	"subtype": "",
	"card_set": "Dagobah",
	"icons": "",
	"Lore": "'Protocol droids are programmed to interface with a variety of computer technologies. Quick and precise interpretation can dramatically increase operational efficiency.',",
	"Rarity": "R",
	"Text": "'Use 3 Force to deploy on your side of the table (free if C-3PO on table). If you have a protocol droid aboard a starship or vehicle in a battle, you may use X Force to reduce the battle damage against you by X (by X + 1 if a Nav Computer character is also aboard).',",
	"Destiny": "4",
	"Power": "",
	"Ability": "",
	"Deploy": "",
	"Forfeit": "",
	"Hyperspeed": "",
	"Maneuver": "",
	"Parsec": "",
	"path": "/starwars/Dagobah-Light/t_theprofessor",
	"uniqueness": "•",
	"ModelType": "",
	"ObjectiveText1": "",
	"ObjectiveText2": "",
	"ForceIconsD": "",
	"ForceIconsL": "",
	"Armor": "",
	"CreatureDV": "",
	"Landspeed": "",
	"Politics": "",
	"Influence": "",
	"LocationDStext": "",
	"LocationLStext": "",
	"ObjectiveFrontName": "",
	"ObjectiveBackName": "",
	"Luck": "",
	"Shadow": "",
}
