{
	"name": "TIE Vanguard",
	"id": "138691",
	"side": "DS",
	"type": "Starship",
	"subtype": "Starfighter",
	"card_set": "A New Hope",
	"icons": "Pilot",
	"Lore": "'Reconnaissance starfighter. Often deployed first to gather detailed information on enemy starship movement before full fleet engagement.',",
	"Rarity": "C2",
	"Text": "'Permanent pilot provides ability of 1. You may deploy cards to same system or sector as a ''react''.',",
	"Destiny": "3",
	"Power": "1",
	"Ability": "",
	"Deploy": "2",
	"Forfeit": "3",
	"Hyperspeed": "",
	"Maneuver": "2",
	"Parsec": "",
	"path": "/starwars/ANewHope-Dark/t_tievanguard",
	"uniqueness": "",
	"ModelType": "TIE/RC",
	"ObjectiveText1": "",
	"ObjectiveText2": "",
	"ForceIconsD": "",
	"ForceIconsL": "",
	"Armor": "",
	"CreatureDV": "",
	"Landspeed": "",
	"Politics": "",
	"Influence": "",
	"LocationDStext": "",
	"LocationLStext": "",
	"ObjectiveFrontName": "",
	"ObjectiveBackName": "",
	"Luck": "",
	"Shadow": "",
}
