{
	"name": "Vader's Anger (V)",
	"id": "138096",
	"side": "DS",
	"type": "Interrupt",
	"subtype": "Lost",
	"card_set": "Virtual Block 5",
	"icons": "[Tatooine]",
	"Lore": "'Anger and aggression fuel the dark side of the Force.',",
	"Rarity": "C",
	"Text": "'During any move phase, initiate an epic duel between Vader and a Jedi present with him. Both players draw two destiny and add power. Loser (lowest total) is placed in Used Pile (if Epic Duel on table, Lost Pile instead), losing player loses 2 Force (cannot be reduced), and winning player may retrieve 2 Force.(Errata Text - September 9th, 2009)',",
	"Destiny": "5",
	"Power": "",
	"Ability": "",
	"Deploy": "",
	"Forfeit": "",
	"Hyperspeed": "",
	"Maneuver": "",
	"Parsec": "",
	"path": "/starwars/Virtual5-Dark/t_vadersanger",
	"uniqueness": "•",
	"ModelType": "",
	"ObjectiveText1": "",
	"ObjectiveText2": "",
	"ForceIconsD": "",
	"ForceIconsL": "",
	"Armor": "",
	"CreatureDV": "",
	"Landspeed": "",
	"Politics": "",
	"Influence": "",
	"LocationDStext": "",
	"LocationLStext": "",
	"ObjectiveFrontName": "",
	"ObjectiveBackName": "",
	"Luck": "",
	"Shadow": "",
}
