{
	"name": "Wooof (V)",
	"id": "137196",
	"side": "DS",
	"type": "Character",
	"subtype": "Alien",
	"card_set": "Virtual Block 3",
	"icons": "Pilot  [Jabba's Palace]",
	"Lore": "'Kadas''sa''Nikto. One of Jabba''s best pilots. Often pilots Jabba''s space yacht. Smuggler. Prefers to be flying combat starfighters.',",
	"Rarity": "R",
	"Text": "'Adds 3 to power of anything he pilots. Wooof may deploy with any cruiser using Combat Response. When deployed, may draw top card from Reserve Deck. During your deploy phase, if piloting Jabba''s Space Cruiser, may deploy one Jabba aboard (for free) from Reserve Deck; reshuffle.',",
	"Destiny": "3",
	"Power": "2",
	"Ability": "2",
	"Deploy": "2",
	"Forfeit": "4",
	"Hyperspeed": "",
	"Maneuver": "",
	"Parsec": "",
	"path": "/starwars/Virtual3-Dark/t_wooof",
	"uniqueness": "•",
	"ModelType": "",
	"ObjectiveText1": "",
	"ObjectiveText2": "",
	"ForceIconsD": "",
	"ForceIconsL": "",
	"Armor": "",
	"CreatureDV": "",
	"Landspeed": "",
	"Politics": "",
	"Influence": "",
	"LocationDStext": "",
	"LocationLStext": "",
	"ObjectiveFrontName": "",
	"ObjectiveBackName": "",
	"Luck": "",
	"Shadow": "",
}
