{
	"name": "Yavin 4: Massassi Ruins",
	"id": "136661",
	"side": "LS",
	"type": "Location",
	"subtype": "Site",
	"card_set": "A New Hope",
	"icons": "[Exterior]  [Planet]",
	"Lore": "'',",
	"Rarity": "U1",
	"Text": "'',",
	"Destiny": "0",
	"Power": "",
	"Ability": "",
	"Deploy": "",
	"Forfeit": "",
	"Hyperspeed": "",
	"Maneuver": "",
	"Parsec": "",
	"path": "/starwars/ANewHope-Light/t_yavin4massassiruins",
	"uniqueness": "•",
	"ModelType": "",
	"ObjectiveText1": "",
	"ObjectiveText2": "",
	"ForceIconsD": "0",
	"ForceIconsL": "2",
	"Armor": "",
	"CreatureDV": "",
	"Landspeed": "",
	"Politics": "",
	"Influence": "",
	"LocationDStext": "If you control, Force drain +1 here.",
	"LocationLStext": "If you control, with a leader here, your starships are each power +1 at Death Star system.",
	"ObjectiveFrontName": "",
	"ObjectiveBackName": "",
	"Luck": "",
	"Shadow": "",
}
