{
	"name": "Yoda, Senior Council Member (V) (AI)",
	"id": "135390",
	"side": "LS",
	"type": "Character",
	"subtype": "Jedi Master",
	"card_set": "Virtual Block 5",
	"icons": "[Episode 1]  [Coruscant]",
	"Lore": "'Senior Jedi Council member. Responsible for the early training of Obi-Wan Kenobi. When Qui-Gon brought Anakin before the Council, Yoda voted not to train the boy.',",
	"Rarity": "R",
	"Text": "'Deploys only to [Episode I] sites. While at Jedi Council Chamber, immune to attrition, Jedi are deploy -2 here, and (unless a Dark Jedi here) other Jedi may treat ''Jedi Council Chamber'' in their game text as ''[Episode I] battleground sites.''(Original concept by Jacob Taylor - PC Volunteer Award 2005)',",
	"Destiny": "1",
	"Power": "3",
	"Ability": "7",
	"Deploy": "4",
	"Forfeit": "7",
	"Hyperspeed": "",
	"Maneuver": "",
	"Parsec": "",
	"path": "/starwars/Virtual5-Light/t_yodaseniorcouncilmemberai",
	"uniqueness": "•",
	"ModelType": "",
	"ObjectiveText1": "",
	"ObjectiveText2": "",
	"ForceIconsD": "",
	"ForceIconsL": "",
	"Armor": "",
	"CreatureDV": "",
	"Landspeed": "",
	"Politics": "",
	"Influence": "",
	"LocationDStext": "",
	"LocationLStext": "",
	"ObjectiveFrontName": "",
	"ObjectiveBackName": "",
	"Luck": "",
	"Shadow": "",
}
